{
    "UrlLocal": "spain_laliga/2014-2015/2015-02-14 - 20-00 Real Madrid 2 - 0 Dep. La Coruna/",
    "UrlYoutube": "",
    "annotations": [
        {
            "gameTime": "1 - 22:00",
            "label": "soccer-ball",
            "team": "home"
        },
        {
            "gameTime": "1 - 44:26",
            "label": "y-card",
            "team": "away"
        },
        {
            "gameTime": "2 - 02:34",
            "label": "y-card",
            "team": "home"
        },
        {
            "gameTime": "2 - 15:42",
            "label": "y-card",
            "team": "away"
        },
        {
            "gameTime": "2 - 19:41",
            "label": "substitution-in",
            "team": "away"
        },
        {
            "gameTime": "2 - 25:35",
            "label": "substitution-in",
            "team": "home"
        },
        {
            "gameTime": "2 - 27:17",
            "label": "soccer-ball",
            "team": "home"
        },
        {
            "gameTime": "2 - 32:45",
            "label": "y-card",
            "team": "home"
        },
        {
            "gameTime": "2 - 33:52",
            "label": "substitution-in",
            "team": "away"
        },
        {
            "gameTime": "2 - 34:48",
            "label": "substitution-in",
            "team": "home"
        },
        {
            "gameTime": "2 - 37:41",
            "label": "y-card",
            "team": "away"
        },
        {
            "gameTime": "2 - 39:00",
            "label": "substitution-in",
            "team": "away"
        },
        {
            "gameTime": "2 - 40:38",
            "label": "substitution-in",
            "team": "home"
        },
        {
            "gameTime": "2 - 43:18",
            "label": "y-card",
            "team": "away"
        }
    ],
    "gameAwayTeam": "Dep. La Coruna",
    "gameDate": "14/02/2015 - 20:00",
    "gameHomeTeam": "Real Madrid",
    "gameScore": "2 - 0"
}