{
    "UrlLocal": "england_epl/2016-2017/2016-11-26 - 18-00 Liverpool 2 - 0 Sunderland/",
    "UrlYoutube": "",
    "annotations": [
        {
            "gameTime": "1 - 33:18",
            "label": "substitution-in",
            "team": "home"
        },
        {
            "gameTime": "2 - 14:56",
            "label": "y-card",
            "team": "away"
        },
        {
            "gameTime": "2 - 18:24",
            "label": "y-card",
            "team": "away"
        },
        {
            "gameTime": "2 - 21:19",
            "label": "y-card",
            "team": "home"
        },
        {
            "gameTime": "2 - 24:52",
            "label": "y-card",
            "team": "away"
        },
        {
            "gameTime": "2 - 29:44",
            "label": "soccer-ball",
            "team": "home"
        },
        {
            "gameTime": "2 - 33:25",
            "label": "substitution-in",
            "team": "away"
        },
        {
            "gameTime": "2 - 33:35",
            "label": "substitution-in",
            "team": "away"
        },
        {
            "gameTime": "2 - 41:48",
            "label": "substitution-in",
            "team": "home"
        },
        {
            "gameTime": "2 - 45:10",
            "label": "soccer-ball",
            "team": "home"
        },
        {
            "gameTime": "2 - 46:56",
            "label": "substitution-in",
            "team": "home"
        }
    ],
    "gameAwayTeam": "Sunderland",
    "gameDate": "26/11/2016 - 18:00",
    "gameHomeTeam": "Liverpool",
    "gameScore": "2 - 0"
}