{
    "UrlLocal": "germany_bundesliga/2015-2016/2015-08-29 - 19-30 Bayern Munich 3 - 0 Bayer Leverkusen/",
    "UrlYoutube": "",
    "annotations": [
        {
            "gameTime": "1 - 05:15",
            "label": "y-card",
            "team": "away"
        },
        {
            "gameTime": "1 - 07:35",
            "label": "y-card",
            "team": "home"
        },
        {
            "gameTime": "1 - 17:58",
            "label": "y-card",
            "team": "away"
        },
        {
            "gameTime": "1 - 17:58",
            "label": "y-card",
            "team": "home"
        },
        {
            "gameTime": "1 - 25:48",
            "label": "soccer-ball",
            "team": "home"
        },
        {
            "gameTime": "2 - 00:00",
            "label": "substitution-in",
            "team": "away"
        },
        {
            "gameTime": "2 - 14:30",
            "label": "soccer-ball",
            "team": "home"
        },
        {
            "gameTime": "2 - 15:18",
            "label": "substitution-in",
            "team": "away"
        },
        {
            "gameTime": "2 - 25:07",
            "label": "soccer-ball",
            "team": "home"
        },
        {
            "gameTime": "2 - 26:13",
            "label": "y-card",
            "team": "away"
        },
        {
            "gameTime": "2 - 27:12",
            "label": "substitution-in",
            "team": "home"
        },
        {
            "gameTime": "2 - 32:22",
            "label": "substitution-in",
            "team": "away"
        },
        {
            "gameTime": "2 - 32:20",
            "label": "substitution-in",
            "team": "home"
        },
        {
            "gameTime": "2 - 36:49",
            "label": "substitution-in",
            "team": "home"
        }
    ],
    "gameAwayTeam": "Bayer Leverkusen",
    "gameDate": "29/08/2015 - 19:30",
    "gameHomeTeam": "Bayern Munich",
    "gameScore": "3 - 0"
}